eltako14bus-0.0.79.dist-info/licenses/LICENSE
eltakobus/__init__.py
eltakobus/bus.py
eltakobus/coap.py
eltakobus/device.py
eltakobus/eep.py
eltakobus/error.py
eltakobus/locking.py
eltakobus/message.py
eltakobus/serial.py
eltakobus/util.py
tests/__init__.py
tests/generic_eep_test.py
eltako14bus-0.0.79.dist-info/METADATA
eltako14bus-0.0.79.dist-info/WHEEL
eltako14bus-0.0.79.dist-info/top_level.txt
eltako14bus-0.0.79.dist-info/RECORD
