Metadata-Version: 2.4
Name: eltako14bus
Version: 0.0.79
Summary: Library for participating in the Eltako Series 14 RS485 bus
Home-page: https://github.com/grimmpp/eltako14bus
Author: chrysn, grimmpp
Author-email: chrysn@fsfe.org, grimmpp14@gmail.com
Classifier: Programming Language :: Python :: 3
Classifier: License :: OSI Approved :: GNU Lesser General Public License v3 or later (LGPLv3+)
License-File: LICENSE
Provides-Extra: serial
Requires-Dist: pyserial_asyncio; extra == "serial"
Requires-Dist: pyserial>=3.4; extra == "serial"
Provides-Extra: coap
Requires-Dist: aiocoap==0.4a1; extra == "coap"
Provides-Extra: eltakotool
Requires-Dist: pyyaml; extra == "eltakotool"
Requires-Dist: pyxdg; extra == "eltakotool"
Dynamic: author
Dynamic: author-email
Dynamic: classifier
Dynamic: description
Dynamic: description-content-type
Dynamic: home-page
Dynamic: license-file
Dynamic: provides-extra
Dynamic: summary
